fusepyng.py
fusepyng-2.0.0.dist-info/LICENSE
fusepyng-2.0.0.dist-info/METADATA
fusepyng-2.0.0.dist-info/WHEEL
fusepyng-2.0.0.dist-info/top_level.txt
fusepyng-2.0.0.dist-info/RECORD
