Metadata-Version: 2.1
Name: fusepyng
Version: 2.0.0
Summary: Simple ctypes bindings for FUSE
Author: Giorgos Verigakis
Author-email: verigak@gmail.com
Maintainer: Rian Hunter
Maintainer-email: rian@alum.mit.edu
License: ISC
Classifier: Intended Audience :: Developers
Classifier: License :: OSI Approved :: ISC License (ISCL)
Classifier: Operating System :: MacOS
Classifier: Operating System :: POSIX
Classifier: Operating System :: Unix
Classifier: Programming Language :: Python :: 3
Classifier: Topic :: System :: Filesystems
License-File: LICENSE
